AUTHORS
ChangeLog
LICENSE
MANIFEST.in
README.rst
requirements.txt
run_tests.sh
setup.cfg
setup.py
test-requirements.txt
tox.ini
tests/__init__.py
tests/unit/__init__.py
tests/unit/test_pulls.py
tests/unit/test_reports.py
tugboat/__init__.py
tugboat/pulls.py
tugboat/reports.py
tugboat.egg-info/PKG-INFO
tugboat.egg-info/SOURCES.txt
tugboat.egg-info/dependency_links.txt
tugboat.egg-info/entry_points.txt
tugboat.egg-info/not-zip-safe
tugboat.egg-info/requires.txt
tugboat.egg-info/top_level.txt